inol_rest/__init__.py
inol_rest/config.py
inol_rest-0.1.12.dist-info/DESCRIPTION.rst
inol_rest-0.1.12.dist-info/METADATA
inol_rest-0.1.12.dist-info/RECORD
inol_rest-0.1.12.dist-info/WHEEL
inol_rest-0.1.12.dist-info/metadata.json
inol_rest-0.1.12.dist-info/top_level.txt
