Metadata-Version: 2.0
Name: inol-rest
Version: 0.1.12
Summary: Inol RESTful API
Home-page: https://github.com/awalker125/inol_rest
Author: awalker125
Author-email: awalker125@users.noreply.github.com
License: MIT
Keywords: inol api
Platform: UNKNOWN
Classifier: Development Status :: 2 - Pre-Alpha
Classifier: License :: OSI Approved :: MIT License
Classifier: Operating System :: OS Independent
Classifier: Programming Language :: Python :: 2.7
Requires-Python: >=2.7
Requires-Dist: futures
Requires-Dist: flask
